pytest_envx-2.0.0.dist-info/METADATA
pytest_envx-2.0.0.dist-info/WHEEL
pytest_envx-2.0.0.dist-info/entry_points.txt
pytest_envx-2.0.0.dist-info/licenses/LICENSE.txt
pytest_envx/__init__.py
pytest_envx/__version__.py
pytest_envx/plugin.py
pytest_envx/py.typed
pytest_envx-2.0.0.dist-info/RECORD
