Metadata-Version: 2.1
Name: pytest-envx
Version: 2.0.0
Summary: Pytest plugin for managing environment variables with interpolation and .env file support.
Author-Email: Eugene Liukin <eugeneliukin.dev@gmail.com>
License: MIT
Classifier: Development Status :: 4 - Beta
Classifier: Intended Audience :: Developers
Classifier: License :: OSI Approved :: MIT License
Classifier: Operating System :: OS Independent
Classifier: Programming Language :: Python :: 3
Classifier: Programming Language :: Python :: 3.9
Classifier: Programming Language :: Python :: 3.10
Classifier: Programming Language :: Python :: 3.11
Classifier: Programming Language :: Python :: 3.12
Classifier: Programming Language :: Python :: 3.13
Classifier: Framework :: Pytest
Classifier: Environment :: Plugins
Classifier: Typing :: Typed
Classifier: Topic :: Software Development :: Libraries :: Python Modules
Classifier: Topic :: Software Development :: Testing
Project-URL: Homepage, https://github.com/eugeneliukindev/pytest-envx
Project-URL: Repository, https://github.com/eugeneliukindev/pytest-envx
Project-URL: Issues, https://github.com/eugeneliukindev/pytest-envx/issues
Project-URL: Changelog, https://github.com/eugeneliukindev/pytest-envx/releases
Requires-Python: >=3.9
Requires-Dist: pytest>=8.4.1
Requires-Dist: python-dotenv>=1.1.0
Requires-Dist: tomli>=2.2.1; python_version < "3.11"
